oresapi/__init__.py
oresapi/about.py
oresapi/oresapi.py
oresapi/session.py
oresapi/utilities/__init__.py
oresapi/utilities/score_revisions.py
oresapi-0.1.0.dist-info/LICENSE
oresapi-0.1.0.dist-info/METADATA
oresapi-0.1.0.dist-info/WHEEL
oresapi-0.1.0.dist-info/entry_points.txt
oresapi-0.1.0.dist-info/top_level.txt
oresapi-0.1.0.dist-info/RECORD
