Metadata-Version: 2.1
Name: oresapi
Version: 0.1.0
Summary: A set of utilities for efficiently querying the ORES api.
Home-page: https://github.com/halfak/oresapi
Author: Aaron Halfaker
Author-email: ahalfaker@wikimedia.org
License: MIT
Platform: UNKNOWN
Classifier: Development Status :: 3 - Alpha
Classifier: Programming Language :: Python
Classifier: Programming Language :: Python :: 3
Classifier: Environment :: Other Environment
Classifier: Intended Audience :: Developers
Classifier: License :: OSI Approved :: MIT License
Classifier: Operating System :: OS Independent
Requires-Python: >=3
Requires-Dist: more-itertools
Requires-Dist: requests
